lmind/__init__.py
lmind/cli.py
lmind/constants.py
lmind/lmd.py
lmind/settings.py
lmind/task.py
lmind/utils.py
lmind-0.1.5.dist-info/LICENSE
lmind-0.1.5.dist-info/METADATA
lmind-0.1.5.dist-info/WHEEL
lmind-0.1.5.dist-info/entry_points.txt
lmind-0.1.5.dist-info/top_level.txt
lmind-0.1.5.dist-info/RECORD
