Metadata-Version: 2.1
Name: lmind
Version: 0.1.5
Summary: A simple Python library for easily manage project by using the command.
Home-page: https://gitee.com/zsq_tee/lmind
Author: Shuiqing Zheng
Author-email: shuiqingzheng@126.com
License: MIT
Project-URL: Documentation, https://gitee.com/zsq_tee/lmind
Project-URL: Source, https://gitee.com/zsq_tee/lmind
Platform: UNKNOWN
Requires-Python: >=3.6
License-File: LICENSE
Requires-Dist: PTable (>=0.9.2)
